bilateral_truth/__init__.py
bilateral_truth/assertions.py
bilateral_truth/cli.py
bilateral_truth/llm_evaluators.py
bilateral_truth/model_router.py
bilateral_truth/truth_values.py
bilateral_truth/zeta_function.py
bilateral_truth-0.2.1.dist-info/licenses/LICENSE
bilateral_truth-0.2.1.dist-info/METADATA
bilateral_truth-0.2.1.dist-info/WHEEL
bilateral_truth-0.2.1.dist-info/entry_points.txt
bilateral_truth-0.2.1.dist-info/top_level.txt
bilateral_truth-0.2.1.dist-info/RECORD
