Metadata-Version: 2.4
Name: bilateral-truth
Version: 0.2.1
Summary: Caching bilateral factuality evaluation using generalized truth values
Author: Bradley Allen
Author-email: Bradley Allen <b.p.allen@uva.nl>
Maintainer-email: Bradley Allen <b.p.allen@uva.nl>
License-Expression: MIT
Project-URL: Homepage, https://github.com/bradleyallen/bilateral-truth
Project-URL: Repository, https://github.com/bradleyallen/bilateral-truth
Project-URL: Documentation, https://github.com/bradleyallen/bilateral-truth#readme
Project-URL: Bug Tracker, https://github.com/bradleyallen/bilateral-truth/issues
Keywords: factuality,truth-values,bilateral-evaluation,llm,ai-safety,logic,verification
Classifier: Development Status :: 3 - Alpha
Classifier: Intended Audience :: Science/Research
Classifier: Programming Language :: Python :: 3
Classifier: Programming Language :: Python :: 3.9
Classifier: Programming Language :: Python :: 3.10
Classifier: Programming Language :: Python :: 3.11
Classifier: Programming Language :: Python :: 3.12
Classifier: Topic :: Scientific/Engineering :: Mathematics
Classifier: Topic :: Scientific/Engineering :: Artificial Intelligence
Classifier: Topic :: Software Development :: Libraries :: Python Modules
Requires-Python: >=3.9
License-File: LICENSE
Requires-Dist: requests>=2.25.0
Requires-Dist: python-dotenv>=0.19.0
Provides-Extra: dev
Requires-Dist: pytest>=6.0; extra == "dev"
Requires-Dist: pytest-cov>=2.0; extra == "dev"
Requires-Dist: black>=21.0; extra == "dev"
Requires-Dist: flake8>=3.8; extra == "dev"
Requires-Dist: mypy>=0.910; extra == "dev"
Provides-Extra: openai
Requires-Dist: openai>=1.0.0; extra == "openai"
Provides-Extra: anthropic
Requires-Dist: anthropic>=0.3.0; extra == "anthropic"
Provides-Extra: all
Requires-Dist: openai>=1.0.0; extra == "all"
Requires-Dist: anthropic>=0.3.0; extra == "all"
Dynamic: author
Dynamic: license-file
Dynamic: requires-python
